museum_api/__init__.py
museum_api/museumapi.py
museum_api/utils.py
museum_api_package-0.1.1.dist-info/LICENSE
museum_api_package-0.1.1.dist-info/METADATA
museum_api_package-0.1.1.dist-info/WHEEL
museum_api_package-0.1.1.dist-info/top_level.txt
museum_api_package-0.1.1.dist-info/RECORD
