Metadata-Version: 2.1
Name: museum-api-package
Version: 0.1.1
Summary: Python package for implementing functionalities of museum api through objects
Home-page: https://github.com/VinayArora404219/museum-api
Author: Vinay Arora
Author-email: vinayarora404219@protonmail.com
License: UNKNOWN
Project-URL: Bug Tracker, https://github.com/VinayArora404219/museum-api/issues
Platform: UNKNOWN
Classifier: Programming Language :: Python :: 3
Classifier: License :: OSI Approved :: MIT License
Classifier: Operating System :: OS Independent
Requires-Python: >=3.6
License-File: LICENSE
Requires-Dist: requests (==2.26.0)
Requires-Dist: pandas (==1.3.5)
Requires-Dist: lxml (==4.7.1)
Requires-Dist: pdfkit (==1.0.0)
Requires-Dist: openpyxl (==3.0.9)
Requires-Dist: numpy (==1.21.4)
Requires-Dist: urllib3 (==1.26.7)
